{"yaosaijueding001": {"app": [], "update": 0, "enable": false, "status": 5}, "cuqikk0721": {"app": [2125090], "update": 1707034763, "enable": true}, "gunhead01": {"app": [704000], "update": 1707034762, "enable": true}, "svvib92669": {"app": [1337520], "update": 1707034764, "enable": true}, "yihpe56448": {"app": [1751350], "update": 1707034764, "enable": true}, "sfohv57334": {"app": [2593900], "update": 1707034764, "enable": true}, "mqdrw47547": {"app": [413410, 413420, 567640], "update": 1707034766, "enable": true}, "21823670": {"app": [1681430, 2436842], "update": 1707034763, "enable": true}, "taosheng431": {"app": [], "update": 0, "enable": false, "status": 43}, "meloreion": {"app": [], "update": 0, "enable": false, "status": 63}, "banmagame0046": {"app": [], "update": 0, "enable": false, "status": 43}, "banmagame6427": {"app": [], "update": 0, "enable": false, "status": 43}, "banmagame1103": {"app": [], "update": 0, "enable": false, "status": 43}, "banmagame8733": {"app": [], "update": 0, "enable": false, "status": 43}, "qaugw30877": {"app": [1182090], "update": 1707034763, "enable": true}, "47233357": {"app": [1735700], "update": 1707034765, "enable": true}, "36363359": {"app": [1735700], "update": 1707034767, "enable": true}, "xebqk71569": {"app": [1888160], "update": 1707034768, "enable": true}, "jyhca12624": {"app": [1627720], "update": 1707034768, "enable": true}, "DeSDy7773": {"app": [1687950], "update": 1707034769, "enable": true}, "kw7xi3sn0xd4": {"app": [], "update": 0, "enable": false, "status": 5}, "ha1hn0ub8rc6": {"app": [1657630, 433340], "update": 1707034766, "enable": true}, "50141996": {"app": [1868140], "update": 1707034768, "enable": true}, "8735515147": {"app": [1274600], "update": 1707034768, "enable": true}, "47587391": {"app": [2136740], "update": 1707034769, "enable": true}, "zc81UOjt": {"app": [], "update": 0, "enable": false, "status": 5}, "myfjw39589": {"app": [2548950], "update": 1707034769, "enable": true}, "Tserelab": {"app": [], "update": 0, "enable": false, "status": 5}, "bejdw17580": {"app": [220240, 226470, 552520, 939960], "update": 1707034779, "enable": true}, "teq7886": {"app": [], "update": 0, "enable": false, "status": 5}, "svmmw6271": {"app": [1151640], "update": 1707034772, "enable": true}, "aali02566": {"app": [], "update": 0, "enable": false, "status": 5}, "maaartiinn1": {"app": [431960, 1790230, 704850, 1509960, 244210, 12200, 460930, 3590, 331160, 301760], "update": 1707034782, "enable": true}, "vAbuDy": {"app": [10180, 10190, 431960, 1790230, 953880, 967050], "update": 1707034773, "enable": true}, "83013169": {"app": [976310], "update": 1707034771, "enable": true}, "eyhv4887": {"app": [], "update": 0, "enable": false, "status": 5}, "liugezh1": {"app": [275850, 475550, 553670], "update": 1707034772, "enable": true}, "mojnmgudio": {"app": [], "update": 0, "enable": false, "status": 5}, "swmfgy": {"app": [2103140], "update": 1707034772, "enable": true}, "tkops1": {"app": [], "update": 0, "enable": false, "status": 5}, "emirisgoated": {"app": [], "update": 0, "enable": false, "status": 43}, "gflgn72587": {"app": [2050650, 632470, 977950, 2016420, 1027880, 431960, 1790230, 1938090, 632360, 1180760, 1337520, 2673200, 1236890, 1548850, 1227890, 1390150, 2495450], "update": 1707034790, "enable": true}, "md02641": {"app": [737520, 1649730, 1954200, 2140250, 1036640, 400910, 624822, 245850, 322330, 343050, 1483870, 945360, 1097150, 1238810, 1335790, 1057680, 668630, 1508920, 454650, 788100, 386940, 1509960, 504230, 274190, 431960, 1790230, 50130, 360430, 1030830, 1030840, 1421480, 1222680, 1252330, 692890, 1475810, 1364020, 1386620, 587260, 1972440, 1920490, 622680, 1140890, 767930, 220440, 601150, 899440, 261110], "update": 1707034797, "enable": true}, "vlcq89982": {"app": [1326470, 2465200], "update": 1707034778, "enable": true}, "ojzo36629": {"app": [413150], "update": 1707034776, "enable": true}, "irq85580": {"app": [1952250], "update": 1707034778, "enable": true}, "ueru69941": {"app": [19680, 761830, 1009560, 2321830, 1557320, 1882510], "update": 1707034778, "enable": true}, "extca30541": {"app": [255710], "update": 1707034790, "enable": true}, "tflds43165": {"app": [1656780, 1217060, 358130, 1040230], "update": 1707034783, "enable": true}, "jiaoaohehe188888": {"app": [1091500, 1495710, 7530, 663730, 659090, 386280, 624822, 1262780], "update": 1707034784, "enable": true}, "gtfbx25813": {"app": [275850], "update": 1707034783, "enable": true}, "jiaoaohehe9625610": {"app": [618140, 1091500, 1495710], "update": 1707034785, "enable": true}, "oxuu49660": {"app": [377160], "update": 1707034791, "enable": true}, "sigeo694": {"app": [938560], "update": 1707034787, "enable": true}, "RGyQH8771": {"app": [673450, 755980, 2144740], "update": 1707034790, "enable": true}, "junjun888666503": {"app": [477770], "update": 1707034791, "enable": true}, "82712116": {"app": [1467920], "update": 1707034790, "enable": true}, "tfej21882": {"app": [1465890, 624822], "update": 1707034792, "enable": true}, "umawu57377": {"app": [337320, 1272320, 681280], "update": 1707034793, "enable": true}, "junjun888666226": {"app": [400910, 431620], "update": 1707034794, "enable": true}, "23255698": {"app": [1928870], "update": 1707034793, "enable": true}, "yudyp20522": {"app": [1091500, 1495710], "update": 1707034794, "enable": true}, "fay60231": {"app": [699130], "update": 1707034795, "enable": true}, "gvzcl6143": {"app": [], "update": 0, "enable": false, "status": 5}, "jiaoaohehe188884": {"app": [384300, 726480, 736580, 842680, 730, 740, 745], "update": 1707034797, "enable": true}, "Xin548516": {"app": [1244090], "update": 1707034796, "enable": true}, "veuxp332": {"app": [751780], "update": 1707034796, "enable": true}, "rzra74664": {"app": [730310, 776530, 798860, 798870, 798880, 892390, 892391, 892392, 892393, 892394, 892395, 892396, 892397, 892398, 956700, 956701, 956702, 956703, 956704, 956705, 956706, 956707, 956708, 956709, 956720, 956721, 956722, 956723, 956724, 956725, 956726, 956727, 956728, 956729, 956730, 956731, 956732, 956733, 956734, 956735, 956736, 956737, 956738, 956739, 956750, 956751, 956752, 956753, 956760, 956761, 956762, 956763, 956764, 956765, 956766, 956767, 956768, 956769, 956770, 956771, 956772, 956860, 956861, 956862, 956863, 956864, 956865, 956866, 956867, 956868, 956869, 956890, 956891, 956892, 956893, 956894, 956895, 956896, 956897, 956898, 956899, 956920, 956921, 956922, 956923, 956924, 956930, 956940, 956941, 956942, 956943, 956944, 956945, 956946, 956947, 956948, 956949, 962300, 962301, 962302, 962303, 962304, 962305, 962306, 963070, 964930, 964931, 964932, 964933, 964934, 964935, 964936, 964937, 964938, 978850, 978851, 978852, 978853, 978854, 978855, 978856, 978857, 978858, 978859, 978860, 978861, 978862, 978863, 978864, 978865, 978866, 978867, 1019960, 1019961, 1019962, 1019963, 1019964, 1019965, 1019966, 1019967, 1019968, 1019969, 1019970, 1019971, 1019980, 1019981, 1019982, 1019983, 1019984, 1019985, 1019986, 1019987, 1019988, 1019989, 1019990, 1019991, 1019992, 1019993, 1019994, 1052520], "update": 1707034808, "enable": true}, "djaso71988": {"app": [733790], "update": 1707034798, "enable": true}, "junjun16681515857": {"app": [226840, 346680, 362890], "update": 1707034803, "enable": true}, "fvm86485": {"app": [1336180], "update": 1707034798, "enable": true}, "kapk876": {"app": [570, 483980, 834070], "update": 1707034804, "enable": true}, "Qf7Nb3Gi6Hq6": {"app": [], "update": 0, "enable": false, "status": 63}, "72654168": {"app": [], "update": 0, "enable": false, "status": 43}, "ieuio688": {"app": [765810], "update": 1707034798, "enable": true}, "9487555749": {"app": [], "update": 0, "enable": false, "status": 5}, "llkczcgxkkxg": {"app": [], "update": 0, "enable": false, "status": 5}, "lknnp9544": {"app": [1388880, 1274570], "update": 1707034801, "enable": true}, "junyi980015010": {"app": [598980], "update": 1707034801, "enable": true}, "cfid179": {"app": [1348300], "update": 1707034801, "enable": true}, "thpcxjmqaguw": {"app": [1086940], "update": 1707034805, "enable": true}, "banmagame3375": {"app": [], "update": 0, "enable": false, "status": 43}, "uijh552": {"app": [1089980], "update": 1707034800, "enable": true}, "64f637a1": {"app": [2239150], "update": 1707034803, "enable": true}, "cwaclrpccpth": {"app": [1086940], "update": 1707034806, "enable": true}, "zelOa3668": {"app": [], "update": 0, "enable": false, "status": 5}, "jvmod00349": {"app": [2084000], "update": 1707034805, "enable": true}, "foor8t": {"app": [242840], "update": 1707034806, "enable": true}, "bsrgd48478": {"app": [1501610], "update": 1707034807, "enable": true}, "dfdnp98858": {"app": [1432100], "update": 1707034807, "enable": true}, "siye4734": {"app": [1370050], "update": 1707034808, "enable": true}, "jiaoaojunjun7541745": {"app": [435530, 624822], "update": 1707034807, "enable": true}, "bmb00276": {"app": [1281590, 1775270], "update": 1707034810, "enable": true}, "siye6149": {"app": [1946700], "update": 1707034810, "enable": true}, "feptt73220": {"app": [1265780, 2374450], "update": 1707034811, "enable": true}, "bvubv9019": {"app": [1770080, 1543280], "update": 1707034811, "enable": true}, "pzsko37578": {"app": [1649010], "update": 1707034811, "enable": true}, "hli60584": {"app": [585710, 982260], "update": 1707034810, "enable": true}, "13289229": {"app": [], "update": 0, "enable": false, "status": 43}, "Et4Pv2Mu4Zo6": {"app": [1868140, 1229240, 1718570], "update": 1707034809, "enable": true}, "AocIBDpc": {"app": [2343600], "update": 1707034809, "enable": true}, "Hunao894891": {"app": [2317820], "update": 1707034812, "enable": true}, "jiaoaohehe188897": {"app": [834740], "update": 1707034813, "enable": true}, "67641318": {"app": [], "update": 0, "enable": false, "status": 43}, "junjun8661226": {"app": [1021770, 1555560], "update": 1707032492, "enable": true}, "31220593": {"app": [1492730, 2064440], "update": 1707034812, "enable": true}, "89771917": {"app": [], "update": 0, "enable": false, "status": 43}, "32817638": {"app": [], "update": 0, "enable": false, "status": 43}, "junjun888666529": {"app": [202970, 202990, 212910, 230290, 777240], "update": 1707032498, "enable": true}, "liugetu28997": {"app": [247080, 1313140, 1781690, 1492360, 1546400, 2015430, 1388880], "update": 1707034815, "enable": true}, "auxjt03616": {"app": [1161590, 2456610], "update": 1707034814, "enable": true}, "zslwn54577": {"app": [1584940, 624822], "update": 1707034815, "enable": true}, "rzty05869": {"app": [], "update": 0, "enable": false, "status": 43}, "cnwbf42012": {"app": [538030], "update": 1707034814, "enable": true}, "75903597": {"app": [482400], "update": 1707034815, "enable": true}, "hvcmf61753": {"app": [1501610, 1276660, 374040, 1994370], "update": 1707034816, "enable": true}, "junjun888666223": {"app": [691690, 776650, 820860, 640820], "update": 1707034815, "enable": true}, "junjun888666506": {"app": [798290], "update": 1707034818, "enable": true}, "junjun888666520": {"app": [451340, 1354950], "update": 1707034817, "enable": true}, "junjun888666713": {"app": [1189490, 624822], "update": 1707034816, "enable": true}, "junjun888666533": {"app": [282160, 392160, 1239390, 1277600, 1288490], "update": 1707034818, "enable": true}, "sqjzz281": {"app": [], "update": 0, "enable": false, "status": 63}, "junjun888666678": {"app": [578650, 1425430], "update": 1707034820, "enable": true}, "junjun888666524": {"app": [871530, 1208880], "update": 1707034819, "enable": true}, "junjun888666717": {"app": [1094820, 1039890], "update": 1707034820, "enable": true}, "tqkf8942": {"app": [], "update": 0, "enable": false, "status": 5}, "wajueji057": {"app": [29180], "update": 1707034820, "enable": true}, "spga41454": {"app": [684450, 1766280, 1803780, 1803781, 1803782, 2146190], "update": 1707034819, "enable": true}, "85615546": {"app": [2216130], "update": 1707034821, "enable": true}, "junjun888666651": {"app": [42700, 42710, 42720, 42740, 1225780], "update": 1707034824, "enable": true}, "junjun888666557": {"app": [900270], "update": 1707034822, "enable": true}, "youzai4511": {"app": [1956830], "update": 1707034821, "enable": true}, "junjun888666558": {"app": [222750, 791330], "update": 1707034823, "enable": true}, "junjun8886665515": {"app": [446020], "update": 1707034823, "enable": true}, "qyu18713": {"app": [], "update": 0, "enable": false, "status": 43}, "chenxi23669": {"app": [1085160], "update": 1707034824, "enable": true}, "NAzul064192": {"app": [211, 215, 218, 500, 513, 550, 563, 564, 222860, 223540, 227040, 227050, 994280, 743390, 1117030, 792300, 1093910], "update": 1707032508, "enable": true}, "junjun888666569": {"app": [55230], "update": 1707034824, "enable": true}, "byr29404": {"app": [753420, 40700], "update": 1707034825, "enable": true}, "oqjju498": {"app": [1504500], "update": 1707034825, "enable": true}, "lkncv3638": {"app": [1186400, 1227890, 1390150, 1405470, 1546010], "update": 1707034827, "enable": true}, "36336151": {"app": [1696440, 2602680], "update": 1707034825, "enable": true}, "omcie80274": {"app": [], "update": 0, "enable": false, "status": 43}, "junjun8886665520": {"app": [828740], "update": 1707034827, "enable": true}, "junjun888666802": {"app": [598330], "update": 1707034827, "enable": true}, "wdoyi066": {"app": [40950, 907650, 1498880, 1556900], "update": 1707034831, "enable": true}, "junjun8886665539": {"app": [1082180], "update": 1707034829, "enable": true}, "itkc23344": {"app": [990080], "update": 1707034829, "enable": true}, "junjun8886665532": {"app": [269210, 204450], "update": 1707034830, "enable": true}, "feipindahenga": {"app": [991170], "update": 1707034829, "enable": true}, "vwq68584": {"app": [], "update": 0, "enable": false, "status": 63}, "xbwsr043": {"app": [601840], "update": 1707034832, "enable": true}, "youzai5123": {"app": [1636660, 2139360, 1337920, 624822], "update": 1707034832, "enable": true}, "2025fc66": {"app": [1161580], "update": 1707034833, "enable": true}, "junjun888666544": {"app": [860950, 210970], "update": 1707034832, "enable": true}, "nmd68913": {"app": [967050], "update": 1707034832, "enable": true}, "fiqbd918": {"app": [720560], "update": 1707034833, "enable": true}, "50149076": {"app": [1214470], "update": 1707034835, "enable": true}, "ytcxm632": {"app": [], "update": 0, "enable": false, "status": 43}, "junjun888666582": {"app": [744060], "update": 1707034835, "enable": true}, "junjun888666585": {"app": [270150], "update": 1707034836, "enable": true}, "AAAGGQ059": {"app": [], "update": 0, "enable": false, "status": 63}, "junjun888666578": {"app": [774241, 465200], "update": 1707034836, "enable": true}, "ulmkd220": {"app": [1163140], "update": 1707034835, "enable": true}, "junjun888666575": {"app": [269950, 466740, 1513760, 624822], "update": 1707032517, "enable": true}, "junjun888666601": {"app": [1092590], "update": 1707034837, "enable": true}, "junjun888666576": {"app": [960910], "update": 1707034837, "enable": true}, "crdem40003": {"app": [35700, 35720, 690640, 319910, 1683950, 753640, 1355760], "update": 1707034839, "enable": true}, "junjun888666728": {"app": [241260], "update": 1707034840, "enable": true}, "ramdh60927": {"app": [794260, 298110, 322310], "update": 1707034842, "enable": true}, "junjun888666711": {"app": [1012030, 1061010], "update": 1707034839, "enable": true}, "junjun888666665": {"app": [427520], "update": 1707034839, "enable": true}, "wpuye150": {"app": [607080, 1355760], "update": 1707034838, "enable": true}, "junjun8886665535": {"app": [331870, 619150, 1019360], "update": 1707034841, "enable": true}, "yvurp89960": {"app": [2515240], "update": 1707034841, "enable": true}, "30189334": {"app": [], "update": 0, "enable": false, "status": 43}, "junjun888666376": {"app": [431240, 434190], "update": 1707034843, "enable": true}, "dokwfy": {"app": [1264250], "update": 1707032523, "enable": true}, "egpmt91410": {"app": [978780], "update": 1707034841, "enable": true}, "junjun888666396": {"app": [449960, 265300], "update": 1707034844, "enable": true}, "0st3mn": {"app": [252110], "update": 1707034843, "enable": true}, "junjun888666797": {"app": [698160], "update": 1707034844, "enable": true}, "arxdb656": {"app": [582550, 649250, 508440, 218620], "update": 1707034846, "enable": true}, "dbeas787": {"app": [], "update": 0, "enable": false, "status": 63}, "10027265": {"app": [], "update": 0, "enable": false, "status": 43}, "vhgkr16139": {"app": [1545560, 2504700], "update": 1707034845, "enable": true}, "tfj92990": {"app": [943370], "update": 1707034843, "enable": true}, "junjun888666371": {"app": [428550, 449360, 656200, 743930, 624822], "update": 1707034845, "enable": true}, "prcz47780": {"app": [521890, 859570, 1321680, 1951960, 960420], "update": 1707034847, "enable": true}, "tukcb226": {"app": [1186030, 1525890], "update": 1707034847, "enable": true}, "junjun888666359": {"app": [1283960, 578330], "update": 1707034846, "enable": true}, "junjun888666661": {"app": [], "update": 0, "enable": false, "status": 43}, "junjun888666794": {"app": [584400], "update": 1707034847, "enable": true}, "zF74SEMH": {"app": [2196790], "update": 1707034848, "enable": true}, "qloj26233": {"app": [788100, 1396440, 976890], "update": 1707034847, "enable": true}, "wiytr352": {"app": [1293180], "update": 1707034847, "enable": true}, "junjun8886665516": {"app": [1146310], "update": 1707034850, "enable": true}, "35199192": {"app": [], "update": 0, "enable": false, "status": 43}, "Jh6Nb7Aw3Xj2": {"app": [2201940], "update": 1707034850, "enable": true}, "liuge52182": {"app": [], "update": 0, "enable": false, "status": 5}, "junjun888666668": {"app": [826940], "update": 1707034849, "enable": true}, "sm6ob8": {"app": [1154040, 1416260], "update": 1707034853, "enable": true}, "junjun888666672": {"app": [956030], "update": 1707034849, "enable": true}, "junjun888666671": {"app": [798490, 1330380], "update": 1707034851, "enable": true}, "9qbmdy": {"app": [257420, 638380, 1330601], "update": 1707034850, "enable": true}, "yzdik010": {"app": [570, 1146970, 259320], "update": 1707034855, "enable": true}, "jiaoaojunjun21859415": {"app": [1239050], "update": 1707034853, "enable": true}, "tmtth877": {"app": [1410640, 1943700, 1724920], "update": 1707034853, "enable": true}, "wqxq87331": {"app": [], "update": 0, "enable": true}, "j2k25w": {"app": [1163550, 310950], "update": 1707032535, "enable": true}, "liugetu2089": {"app": [934780, 206440, 206450, 346680, 362890, 379430, 868360, 1282550, 641320, 1482320, 1547890, 1368210, 1423900, 1358140, 1250410], "update": 1707034857, "enable": true}, "drdxzafztmxc": {"app": [2399830, 2430930], "update": 1707034856, "enable": true}, "icebl587": {"app": [970830], "update": 1707034855, "enable": true}, "c9di3xx30": {"app": [757320], "update": 1707034854, "enable": true}, "nhiae62785": {"app": [1740720, 334310], "update": 1707034857, "enable": true}, "909smn": {"app": [1181830], "update": 1707034856, "enable": true}, "kejucl": {"app": [852220, 1391990], "update": 1707034857, "enable": true}, "junjun8661229": {"app": [429570], "update": 1707034856, "enable": true}, "szL7yttHs": {"app": [1180660], "update": 1707034858, "enable": true}, "bqsxy925": {"app": [1377380, 1420710], "update": 1707034860, "enable": true}, "qingjugame20": {"app": [1186640], "update": 1707034858, "enable": true}, "jasqs92764": {"app": [2114740, 2500170], "update": 1707034860, "enable": true}, "xxqk725": {"app": [375480], "update": 1707034861, "enable": true}, "junjun8661222": {"app": [618140, 956680], "update": 1707034858, "enable": true}, "nvbtzq": {"app": [1007040], "update": 1707034858, "enable": true}, "646462DSQ": {"app": [], "update": 0, "enable": false, "status": 43}, "eprun62941": {"app": [], "update": 0, "enable": false, "status": 63}, "vllbtz": {"app": [1058770, 624822], "update": 1707034862, "enable": true}, "ozcet7114": {"app": [1076200, 1518160], "update": 1707034861, "enable": true}, "wnjut71387": {"app": [2345020], "update": 1707034861, "enable": true}, "junjun8661223": {"app": [618140, 1245540], "update": 1707034860, "enable": true}, "2ipnpx": {"app": [931280], "update": 1707034860, "enable": true}, "junjun8661224": {"app": [268050], "update": 1707034862, "enable": true}, "ytrv437": {"app": [842100], "update": 1707034864, "enable": true}, "gxklk95056": {"app": [1410710], "update": 1707034864, "enable": true}, "ynpjin": {"app": [1367550], "update": 1707034865, "enable": true}, "5vdaif": {"app": [358130, 1040230], "update": 1707034862, "enable": true}, "liugetewsd52": {"app": [265930, 285710, 334940, 698870, 1918530, 1291340, 1081450, 1954200, 1942280], "update": 1707034865, "enable": true}, "pxje456": {"app": [1302750, 624822], "update": 1707034866, "enable": true}, "smu37015": {"app": [1875310, 1875340], "update": 1707034866, "enable": true}, "vrhgmk": {"app": [677160], "update": 1707034866, "enable": true}, "bgcpx639": {"app": [], "update": 0, "enable": false, "status": 43}, "bklwp439": {"app": [976900], "update": 1707032549, "enable": true}, "kwbi793": {"app": [433550], "update": 1707032549, "enable": true}, "shenling11z": {"app": [], "update": 0, "enable": false, "status": 43}, "xjmwu7": {"app": [587260], "update": 1707032551, "enable": true}, "junjun8661228": {"app": [261030], "update": 1707032552, "enable": true}, "34434943": {"app": [1364210, 1899720, 1901800, 1901840, 1901850, 1903250, 1903920, 1903930, 1904020, 1904840, 1904870], "update": 1707032550, "enable": true}, "Hp6Fs1Jh5Ng2": {"app": [], "update": 0, "enable": false, "status": 43}, "Kp0Um6If2Mm8": {"app": [1170080, 2080330], "update": 1707032551, "enable": true}, "jiaoaojunjun156745164": {"app": [207610], "update": 1707032551, "enable": true}, "ppbug715": {"app": [], "update": 0, "enable": false, "status": 43}, "yn9uni": {"app": [1004750], "update": 1707032553, "enable": true}, "3ohnph": {"app": [301640], "update": 1707032555, "enable": true}, "9821469": {"app": [1999770, 2156230, 2156231, 2156234, 2156235, 2156237, 2156238, 2156239, 2156250, 2156253], "update": 1707032554, "enable": true}, "tlcr81654": {"app": [1594320, 2004660], "update": 1707032555, "enable": true}, "c74ccu": {"app": [671510], "update": 1707032556, "enable": true}, "jiaoao421548763": {"app": [1034160, 577230, 692770, 1520720, 624822], "update": 1707032557, "enable": true}, "vyz91030": {"app": [1970580], "update": 1707032555, "enable": true}, "gfk6413": {"app": [1716740, 2533170, 2561880], "update": 1707032558, "enable": true}, "A15484185": {"app": [1893820], "update": 1707032558, "enable": true}, "7810055496": {"app": [1958220], "update": 1707032557, "enable": true}, "vhnx46131": {"app": [1674890, 1191120, 578650, 1425430, 1670870], "update": 1707034867, "enable": true}, "52761637": {"app": [1931730, 2545420], "update": 1707032560, "enable": true}, "88466477122": {"app": [1931770], "update": 1707032559, "enable": true}, "jkjkcp": {"app": [314650], "update": 1707032560, "enable": true}, "39442252": {"app": [2140850], "update": 1707032559, "enable": true}, "7766985690": {"app": [], "update": 0, "enable": false, "status": 5}, "rpebm616": {"app": [1372810], "update": 1707032561, "enable": true}, "oprsgeppzkzd": {"app": [], "update": 0, "enable": false, "status": 63}, "53147390": {"app": [1650010], "update": 1707032562, "enable": true}, "86xhzfctvt10": {"app": [], "update": 0, "enable": false, "status": 63}, "zqugr384": {"app": [1621690, 1963720], "update": 1707034869, "enable": true}, "jiaoaojunjun3125415": {"app": [1034160, 1397350], "update": 1707032562, "enable": true}, "unkwb223": {"app": [502520], "update": 1707032563, "enable": true}, "mwhbg751": {"app": [1929610], "update": 1707032564, "enable": true}, "lmcuw954": {"app": [1559300], "update": 1707032562, "enable": true}, "edlgx068": {"app": [585020], "update": 1707032562, "enable": true}, "qingjugame13": {"app": [1356670, 1458160], "update": 1707032565, "enable": true}, "junjun86612244": {"app": [], "update": 0, "enable": false, "status": 63}, "rpxhq02742": {"app": [1211600], "update": 1707032565, "enable": true}, "y8u62ozk": {"app": [], "update": 0, "enable": false, "status": 63}, "bdg93654": {"app": [1136370], "update": 1707032564, "enable": true}, "zojko111": {"app": [259680], "update": 1707032567, "enable": true}, "jiaoaohehe15456156": {"app": [1399090], "update": 1707032567, "enable": true}, "xuww246290": {"app": [1184210, 271590], "update": 1707032569, "enable": true}, "nspk8txc": {"app": [1358700], "update": 1707032568, "enable": true}, "vtjls8": {"app": [337340], "update": 1707032569, "enable": true}, "junjun86612255": {"app": [618140, 1116880], "update": 1707034866, "enable": true}, "hah18371": {"app": [1372110], "update": 1707034869, "enable": true}, "wrhd062": {"app": [1221540, 624822], "update": 1707034868, "enable": true}, "ewuiU318": {"app": [1158160], "update": 1707034867, "enable": true}, "mkgw485": {"app": [763890], "update": 1707034868, "enable": true}, "yfpkj5": {"app": [897450], "update": 1707034870, "enable": true}, "yplw684286": {"app": [528230], "update": 1707032572, "enable": true}, "wmsj95633": {"app": [1879330, 1110910], "update": 1707034871, "enable": true}, "qjjzx440": {"app": [1162650], "update": 1707034870, "enable": true}, "kiecn65840": {"app": [1737340], "update": 1707034871, "enable": true}, "udjkk51235": {"app": [1503850], "update": 1707034871, "enable": true}, "incml21151": {"app": [], "update": 0, "enable": false, "status": 5}, "5iekbf": {"app": [893850, 1318140], "update": 1707032572, "enable": true}, "bqnxfe": {"app": [1089630], "update": 1707032572, "enable": true}, "jiaoaojunjun795823": {"app": [597760], "update": 1707032572, "enable": true}, "vzup54455": {"app": [672630, 287450], "update": 1707032574, "enable": true}, "lmzw24123": {"app": [846770, 1269710], "update": 1707032575, "enable": true}, "zd6u0u": {"app": [283640], "update": 1707032575, "enable": true}, "zbuqmm": {"app": [430960], "update": 1707032575, "enable": true}, "2padsw": {"app": [253230, 734880, 607380, 624822], "update": 1707032578, "enable": true}, "t71bsf": {"app": [529180], "update": 1707032575, "enable": true}, "brgoje": {"app": [1115780], "update": 1707032576, "enable": true}, "3x0mjv": {"app": [977500], "update": 1707032576, "enable": true}, "cxhcam": {"app": [1096530], "update": 1707032578, "enable": true}, "iiys7j": {"app": [782570], "update": 1707032578, "enable": true}, "wrwz830": {"app": [1282210, 1299090, 1307540, 1316670, 1333390], "update": 1707032578, "enable": true}, "hzywiv": {"app": [736260], "update": 1707032578, "enable": true}, "Ya3Aj6Im2Qp8": {"app": [], "update": 0, "enable": false, "status": 43}, "vgucbx": {"app": [108800], "update": 1707032580, "enable": true}, "sxz48138": {"app": [844930], "update": 1707032579, "enable": true}, "teq8029": {"app": [1044720, 2789700], "update": 1707032578, "enable": true}, "6ndzkh": {"app": [515570, 738530], "update": 1707032582, "enable": true}, "smhp4f": {"app": [550320], "update": 1707032582, "enable": true}, "xmykzwg": {"app": [982290], "update": 1707032581, "enable": true}, "f2cu81": {"app": [544750], "update": 1707032580, "enable": true}, "otrzo249": {"app": [1128920], "update": 1707032580, "enable": true}, "wfkqj51463": {"app": [1471180, 2017030, 951440, 1698830], "update": 1707032583, "enable": true}, "jiaoaohehe7010520": {"app": [1293160], "update": 1707032583, "enable": true}, "wlrh32353": {"app": [], "update": 0, "enable": false, "status": 5}, "kxomw979": {"app": [], "update": 0, "enable": false, "status": 43}, "jiaoaohehe6554400": {"app": [973810], "update": 1707032585, "enable": true}, "gneht735": {"app": [1372810], "update": 1707032583, "enable": true}, "uhabr256": {"app": [1021100], "update": 1707032584, "enable": true}, "liuge989u2": {"app": [107410, 233800, 390500, 613100, 1471280, 1071870, 1194250, 962130, 940680, 1115690, 1372810], "update": 1707034872, "enable": true}, "junyi525500106": {"app": [1020470], "update": 1707032584, "enable": true}, "inz38962": {"app": [1415660], "update": 1707032586, "enable": true}, "60xmXKqmm44": {"app": [], "update": 0, "enable": false, "status": 43}, "aeopx278": {"app": [787810], "update": 1707032587, "enable": true}, "tnhtl965": {"app": [1297300], "update": 1707032588, "enable": true}, "langchao46607": {"app": [1190460, 1850570], "update": 1707032586, "enable": true}, "jiaoaojunjun795839": {"app": [782330], "update": 1707032588, "enable": true}, "okqxz828": {"app": [1308500], "update": 1707032588, "enable": true}, "dxacbco6487": {"app": [1282730], "update": 1707032586, "enable": true}, "pvyzz044": {"app": [895620], "update": 1707032589, "enable": true}, "cd9b6857": {"app": [1213230], "update": 1707032588, "enable": true}, "tbtqw776": {"app": [1037130], "update": 1707032588, "enable": true}, "jnvpv869": {"app": [869880], "update": 1707032591, "enable": true}, "hrpyj339": {"app": [1323470, 1496960, 1530910, 1556590], "update": 1707032592, "enable": true}, "egpeyb": {"app": [979070], "update": 1707032592, "enable": true}, "naf69840": {"app": [833360], "update": 1707032591, "enable": true}, "gjeee107": {"app": [1042380], "update": 1707032592, "enable": true}, "69gfyzgohw59": {"app": [1539620], "update": 1707032593, "enable": true}, "zowie934": {"app": [1073910], "update": 1707032593, "enable": true}, "djpat164": {"app": [1179060], "update": 1707032592, "enable": true}, "80941678": {"app": [2005160], "update": 1707032594, "enable": true}, "xlfpd016": {"app": [1029780], "update": 1707032595, "enable": true}, "aemhj811": {"app": [1197570], "update": 1707032593, "enable": true}, "klyuj426": {"app": [1318690], "update": 1707032596, "enable": true}, "zmg96826": {"app": [350080], "update": 1707032594, "enable": true}, "ytqbe5407": {"app": [1454400], "update": 1707032595, "enable": true}, "lidde609": {"app": [1544360], "update": 1707032594, "enable": true}, "bglh82816": {"app": [623280], "update": 1707034873, "enable": true}, "jiaoaohehe6052045": {"app": [768520], "update": 1707034871, "enable": true}, "gpdo20627": {"app": [1364100], "update": 1707034872, "enable": true}, "byso88892": {"app": [1569090], "update": 1707034872, "enable": true}, "pwjjj72581": {"app": [1341200, 1684140, 1684141, 1684146, 1684147, 1684148, 1684149, 1684150, 1684151, 1684152, 1684153, 1684154, 1684155, 1684156, 1684157, 1684158, 1684159, 1684160, 1684161, 1684162, 1684163, 1684164, 1684165, 1684166], "update": 1707034877, "enable": true}, "gluox445": {"app": [1447000], "update": 1707034876, "enable": true}, "1d287cf2": {"app": [1416230, 1672540, 1820200, 2054090], "update": 1707032599, "enable": true}, "liugexdtueq": {"app": [], "update": 0, "enable": false, "status": 5}, "rnqq48086": {"app": [1203180, 330020, 374190, 1428100], "update": 1707032600, "enable": true}, "wfjg93792": {"app": [427940], "update": 1707032600, "enable": true}, "kinvu227": {"app": [1253710], "update": 1707032599, "enable": true}, "xwbqr14069": {"app": [1093290, 624822], "update": 1707032600, "enable": true}, "diumz249": {"app": [1414180], "update": 1707032601, "enable": true}, "wcffn095": {"app": [1114070, 2430730], "update": 1707032600, "enable": true}, "liugetuerq": {"app": [], "update": 0, "enable": false, "status": 5}, "44763486": {"app": [], "update": 0, "enable": false, "status": 43}, "61675403": {"app": [1951230], "update": 1707032601, "enable": true}, "36341296": {"app": [1876890], "update": 1707032603, "enable": true}, "zvtxp47744": {"app": [1084020, 1260590], "update": 1707032603, "enable": true}, "Rm4Vn3Nu7Vk9": {"app": [1416050, 2127480, 2093910], "update": 1707032603, "enable": true}, "olzqr58874": {"app": [2230110], "update": 1707032604, "enable": true}, "slaj30473": {"app": [861540], "update": 1707032604, "enable": true}, "xgs68741388": {"app": [], "update": 0, "enable": false, "status": 63}, "te34rUuG": {"app": [2181610], "update": 1707032604, "enable": true}, "liugeagt52dssxx": {"app": [1731070], "update": 1707032605, "enable": true}, "zpkpd85184": {"app": [1750740, 2533870], "update": 1707032604, "enable": true}, "pgpvj51678": {"app": [1591530, 1634690, 1634691, 1634692, 1634693, 1634694, 1634696, 1634697, 1634698, 1634699, 1634700, 1634701, 1634702, 1634703, 1634704, 1634705, 1634706, 1634707, 1634708, 1634709, 1634710, 1634711, 1634712, 1634713, 1649710, 1649711], "update": 1707032609, "enable": true}, "rjewv745": {"app": [1137460], "update": 1707032608, "enable": true}, "ba2zuxqm": {"app": [241930], "update": 1707032608, "enable": true}, "vfifu415": {"app": [], "update": 0, "enable": false, "status": 43}, "bsygh674": {"app": [581630], "update": 1707032609, "enable": true}, "bqrmw463": {"app": [19000], "update": 1707032607, "enable": true}, "lmm97417": {"app": [1283400, 2021380], "update": 1707032609, "enable": true}, "qpijv060": {"app": [], "update": 0, "enable": true}, "rtxep488": {"app": [1361320], "update": 1707032607, "enable": true}, "boefp654": {"app": [1218170], "update": 1707032608, "enable": true}, "rocu28235": {"app": [1584090, 1838750, 1927110, 2122050, 2191950, 2399330], "update": 1707032611, "enable": true}, "ht143182bb": {"app": [1076750], "update": 1707032611, "enable": true}, "ntfs42386": {"app": [894020], "update": 1707032611, "enable": true}, "fcmj42387": {"app": [1097200], "update": 1707032611, "enable": true}, "zukkd18328": {"app": [1110910], "update": 1707034876, "enable": true}, "asme78077": {"app": [1123050], "update": 1707032612, "enable": true}, "gqxoo43451": {"app": [874260], "update": 1707032613, "enable": true}, "ncjj42796": {"app": [1335230, 969760, 1311070], "update": 1707032613, "enable": true}, "dgito775": {"app": [855740], "update": 1707032616, "enable": true}, "scwcocoon": {"app": [1497440], "update": 1707032615, "enable": true}, "junjun8667935": {"app": [33905, 33910, 33930, 33935, 65700, 65720, 65780, 65790, 107430, 219540], "update": 1707032617, "enable": true}, "wnlf14787": {"app": [1108590], "update": 1707032615, "enable": true}, "wiewior2211": {"app": [730, 740, 745, 8930, 16830, 219640, 242760, 556450, 427730, 236850, 4000], "update": 1707034883, "enable": true}, "rkydw12366": {"app": [1138660], "update": 1707032616, "enable": true}, "okpgl742": {"app": [1386780, 1307580], "update": 1707032616, "enable": true}, "aiogk74209": {"app": [1612620], "update": 1707032616, "enable": true}, "bsgf60193": {"app": [1135300, 1151340, 1836200], "update": 1707032621, "enable": true}, "es001239": {"app": [420290, 740130, 282140], "update": 1707032622, "enable": true}, "junyi89200120": {"app": [1489630, 1657900, 1661120, 1777430], "update": 1707032621, "enable": true}, "yfeng053": {"app": [1134710], "update": 1707032618, "enable": true}, "eiyha946": {"app": [1176710], "update": 1707032618, "enable": true}, "cktlg500": {"app": [673610, 1203790], "update": 1707032621, "enable": true}, "pzrn67268": {"app": [908100, 929010], "update": 1707032621, "enable": true}, "lxnwy398": {"app": [892860], "update": 1707032621, "enable": true}, "nmlsq739": {"app": [975680, 1069650], "update": 1707032622, "enable": true}, "ulkeh361": {"app": [1264280, 600480], "update": 1707032623, "enable": true}, "vtml99400": {"app": [914710, 1804200, 712050], "update": 1707032623, "enable": true}, "fxkt44291": {"app": [1434950], "update": 1707032625, "enable": true}, "siye5179": {"app": [871980], "update": 1707032625, "enable": true}, "cdmj76955": {"app": [1644960, 624822], "update": 1707032627, "enable": true}, "cwsz27766": {"app": [233720, 774791, 752590], "update": 1707032623, "enable": true}, "oafw81657": {"app": [1322300], "update": 1707034876, "enable": true}, "dabog456": {"app": [1229460], "update": 1707034877, "enable": true}, "bkul4010": {"app": [1367590], "update": 1707034876, "enable": true}, "vway31386": {"app": [844260], "update": 1707034877, "enable": true}, "afhp73413": {"app": [1198090], "update": 1707034879, "enable": true}, "md31687": {"app": [1356280, 1149620], "update": 1707034881, "enable": true}, "pgoov92245": {"app": [1250760], "update": 1707034880, "enable": true}, "y8u1mepb": {"app": [1708520, 2113540], "update": 1707034881, "enable": true}, "wipkh846": {"app": [1330460], "update": 1707034880, "enable": true}, "ivegq85765": {"app": [976590], "update": 1707034881, "enable": true}, "JTVN4XPZM": {"app": [1563130], "update": 1707034881, "enable": true}, "rnsz6028": {"app": [1104280, 1015890, 638990, 1612740], "update": 1707034883, "enable": true}, "rpzv21952": {"app": [1312960], "update": 1707034882, "enable": true}, "lrt65503": {"app": [1161170], "update": 1707034884, "enable": true}, "md94483": {"app": [1158370, 1797200, 1256830], "update": 1707034884, "enable": true}, "wnhz35249": {"app": [], "update": 0, "enable": false, "status": 63}, "cjuce460": {"app": [1446650], "update": 1707034885, "enable": true}, "tlhrv30600": {"app": [937310], "update": 1707034884, "enable": true}, "ovt28620": {"app": [1919740], "update": 1707034883, "enable": true}, "rhkix88182": {"app": [1723260, 1328840], "update": 1707034886, "enable": true}, "uwxjk11141": {"app": [1638220], "update": 1707034887, "enable": true}, "cdkfr38005": {"app": [921800, 1133130, 1199030, 1224020, 1550510], "update": 1707034887, "enable": true}, "lgxp13058": {"app": [1649830], "update": 1707034887, "enable": true}, "ttjjz69030": {"app": [817130, 624822], "update": 1707034889, "enable": true}, "kaw74408": {"app": [318600], "update": 1707034888, "enable": true}, "brcfa97958": {"app": [1502040], "update": 1707034888, "enable": true}, "xiaosheng5215": {"app": [1251210, 1794680], "update": 1707034888, "enable": true}, "nhggq740": {"app": [1121780, 1832640], "update": 1707034890, "enable": true}, "fanui858": {"app": [1404850], "update": 1707034890, "enable": true}, "plhu64312": {"app": [1266840], "update": 1707034889, "enable": true}, "nav4ypa": {"app": [1192010, 748300], "update": 1707034891, "enable": true}, "siye2602": {"app": [1448260], "update": 1707034889, "enable": true}, "ems54060": {"app": [], "update": 0, "enable": false, "status": 63}, "gameqiumi1": {"app": [374320, 728880, 2321210], "update": 1707034892, "enable": true}, "nhhmf5275": {"app": [900040], "update": 1707034893, "enable": true}, "jhf3546": {"app": [2071280], "update": 1707034893, "enable": true}, "DGwgJdnj": {"app": [2185780], "update": 1707034893, "enable": true}, "pbkhq995": {"app": [], "update": 0, "enable": false, "status": 63}, "rnnmr33839": {"app": [1669980], "update": 1707034891, "enable": true}, "sagze95449": {"app": [1717640, 1963370], "update": 1707034895, "enable": true}, "fyehc662": {"app": [1330660], "update": 1707034895, "enable": true}, "28cb3d32": {"app": [1668690, 1574580, 1634150, 1488810, 952730, 624822], "update": 1707034896, "enable": true}, "sd96fdk4h": {"app": [1562940], "update": 1707034893, "enable": true}, "wohzw168": {"app": [1043260], "update": 1707034896, "enable": true}, "iuxmc82259": {"app": [1406850], "update": 1707034894, "enable": true}, "jqot68037": {"app": [407130, 671970, 983970, 1244630], "update": 1707034895, "enable": true}, "qafw49889": {"app": [1191120], "update": 1707034896, "enable": true}, "vsvt98103": {"app": [1210320], "update": 1707034897, "enable": true}, "fjrtp307": {"app": [1607310], "update": 1707034898, "enable": true}, "srs84257": {"app": [1262350], "update": 1707034896, "enable": true}, "junjun8667931": {"app": [34830, 34870, 271500], "update": 1707034900, "enable": true}, "peel38898": {"app": [1227280, 1832640, 618140], "update": 1707034898, "enable": true}, "oezwa996": {"app": [832360], "update": 1707034898, "enable": true}, "hqwoj12605": {"app": [1101790], "update": 1707034901, "enable": true}, "junjun8667890": {"app": [12810], "update": 1707034900, "enable": true}, "siye5276": {"app": [1217060], "update": 1707034901, "enable": true}, "junjun8667892": {"app": [356570], "update": 1707034901, "enable": true}, "amnuw672": {"app": [], "update": 0, "enable": false, "status": 43}, "yoix48521": {"app": [1286350, 705120, 907470, 927250, 1042490, 1218500], "update": 1707032649, "enable": true}, "qbak84035": {"app": [1435790, 418530, 842180], "update": 1707032648, "enable": true}, "junjun8667897": {"app": [55150, 1759110], "update": 1707032650, "enable": true}, "scwfate": {"app": [1902690, 2407210, 2426930, 1312990], "update": 1707032651, "enable": true}, "hhazjlyf49780": {"app": [], "update": 0, "enable": false, "status": 63}, "vuebr47528": {"app": [670350], "update": 1707032650, "enable": true}, "amfv55000": {"app": [], "update": 0, "enable": true}, "SDgnl976100": {"app": [], "update": 0, "enable": false, "status": 5}, "chengyu9991": {"app": [], "update": 0, "enable": false, "status": 43}, "junjun8667905": {"app": [6800, 6810, 6830, 6840], "update": 1707032651, "enable": true}, "tjtov80516": {"app": [1379600], "update": 1707032651, "enable": true}, "junjun8667907": {"app": [50620, 462780], "update": 1707032651, "enable": true}, "junjun8667917": {"app": [507490], "update": 1707032652, "enable": true}, "junjun8667925": {"app": [1019450], "update": 1707032652, "enable": true}, "hpoar472": {"app": [628770], "update": 1707032653, "enable": true}, "uzy8ro": {"app": [1088850], "update": 1707032655, "enable": true}, "mxayo53017": {"app": [371660, 1426450], "update": 1707034901, "enable": true}, "rbr48994": {"app": [1556790, 2078340], "update": 0, "enable": true}, "ikkq21274": {"app": [2800, 2810, 2840, 2850, 2820, 201310, 2870, 282160, 258990, 258991, 570420, 392160, 1238200, 1239210, 1239170, 1239390, 1277600, 1288490, 1216710], "update": 1707034917, "enable": true}, "youzhai2022e": {"app": [], "update": 0, "enable": false, "status": 63}, "youxic03288": {"app": [230230, 307400, 373420, 428790, 1406850, 1796880, 435150, 664400], "update": 1707034914, "enable": true}, "qjfv53772": {"app": [1154810, 1764390, 1393410], "update": 1707032657, "enable": true}, "van89250": {"app": [1567020, 2285890], "update": 1707032657, "enable": true}, "teq8134a": {"app": [1390410], "update": 1707032656, "enable": true}, "pCoVe10830": {"app": [871980], "update": 1707032658, "enable": true}, "ercod47948": {"app": [1449500, 955050, 1178830], "update": 1707032659, "enable": true}, "22719152": {"app": [1807210], "update": 1707032661, "enable": true}, "csdu67102": {"app": [1063980, 1506980], "update": 1707032659, "enable": true}, "wwgo88481": {"app": [288160, 425580, 456750, 1361320, 538460, 364230, 218640], "update": 1707032663, "enable": true}, "wnlom758": {"app": [955050, 1178830, 624822], "update": 1707032664, "enable": true}, "cebc98103": {"app": [], "update": 0, "enable": true}, "odbeo42353": {"app": [768200, 808040], "update": 1707032664, "enable": true}, "ywxx37154": {"app": [1272160, 1492360], "update": 1707034904, "enable": true}, "bgpc26479": {"app": [1137300, 11050, 11040, 11190, 11140, 209230, 11150, 252890, 209630, 474240, 1250110, 1250710, 205650, 241260, 350640, 1252260, 11180], "update": 1707034917, "enable": true}, "yjtmv67033": {"app": [1266840], "update": 1707034903, "enable": true}, "ubfp22164": {"app": [1244630], "update": 1707034904, "enable": true}, "gc4jn3jh8rj2": {"app": [1182900], "update": 1707032668, "enable": true}, "xcgsc29471": {"app": [1286280, 1390700], "update": 1707032664, "enable": true}, "junjun89930120": {"app": [1559390], "update": 1707032666, "enable": true}, "hr583kan": {"app": [1195290, 1789320, 1091500, 1495710, 1627630, 609320, 1570010, 1920660, 1901380], "update": 1707034908, "enable": true}, "eftr88863": {"app": [1510580, 1151740, 1197590], "update": 1707034905, "enable": true}, "junyi8992350": {"app": [668580], "update": 1707034909, "enable": true}, "tredr5142": {"app": [1337760], "update": 1707034908, "enable": true}, "Di8Uc4Ul3Ly7": {"app": [1811600], "update": 1707034908, "enable": true}, "tuhk37315": {"app": [776490, 774171], "update": 1707034908, "enable": true}, "pvo24272": {"app": [520440], "update": 1707034912, "enable": true}, "nmqnm48575": {"app": [1718870, 653530], "update": 1707034913, "enable": true}, "lpmt300356": {"app": [820540, 203160], "update": 1707034916, "enable": true}, "kmf73756": {"app": [1642790], "update": 1707034912, "enable": true}, "teq7968": {"app": [920210], "update": 1707034915, "enable": true}, "xiaoshenyouxi212": {"app": [820540], "update": 1707034916, "enable": true}, "oarwh266": {"app": [975470], "update": 1707034917, "enable": true}, "apne622": {"app": [1380420], "update": 1707034917, "enable": true}, "ukmn30846": {"app": [], "update": 0, "enable": false, "status": 5}, "mzmtl933": {"app": [], "update": 0, "enable": false, "status": 5}, "temn12504": {"app": [1579380], "update": 1707032675, "enable": true}, "qcxtl69133": {"app": [1025960, 1774980, 522210], "update": 1707032675, "enable": true}, "sqrbj393": {"app": [553420], "update": 1707032675, "enable": true}, "hzsd8411": {"app": [1457520], "update": 1707032677, "enable": true}, "lhyyf34480": {"app": [1341200, 1684140, 1684141], "update": 1707034916, "enable": true}, "vdwn6235": {"app": [368070, 34870, 34830, 34850, 1681970, 1937520], "update": 1707034920, "enable": true}, "teq7839": {"app": [377300, 1797170], "update": 1707034918, "enable": true}, "jhtc7843": {"app": [1296360, 378540, 644830, 1244800], "update": 1707032679, "enable": true}, "etiqb21005": {"app": [1132030], "update": 1707032679, "enable": true}, "zwzye945": {"app": [1363350, 1138850], "update": 1707032678, "enable": true}, "dkjdj45245": {"app": [1580240, 1702330], "update": 1707032678, "enable": true}, "forspoken43": {"app": [2113920], "update": 1707032678, "enable": true}, "nj493662": {"app": [1265820], "update": 1707032679, "enable": true}, "rkrat087": {"app": [1194930, 1149620], "update": 1707034920, "enable": true}, "dksbr70367": {"app": [1032590, 1515900], "update": 1707032682, "enable": true}, "ostqh75248": {"app": [], "update": 0, "enable": false, "status": 5}, "rbjfv8043": {"app": [1432050], "update": 1707032682, "enable": true}, "deme138": {"app": [1658870], "update": 1707032682, "enable": true}, "fuha36835": {"app": [], "update": 0, "enable": false, "status": 5}, "liugetu206698": {"app": [], "update": 0, "enable": true}, "xwspa157": {"app": [], "update": 0, "enable": true}, "pzfnh056": {"app": [], "update": 0, "enable": true}, "zeodu11417": {"app": [], "update": 0, "enable": true}, "fgoti62408": {"app": [], "update": 0, "enable": true}, "xhufg029": {"app": [], "update": 0, "enable": true}, "efgmm75766": {"app": [], "update": 0, "enable": true}, "krct3860": {"app": [], "update": 0, "enable": true}, "czemf42000": {"app": [], "update": 0, "enable": true}, "383a577d": {"app": [], "update": 0, "enable": true}, "26X7UqUmG39": {"app": [], "update": 0, "enable": true}, "banmagame8514": {"app": [], "update": 0, "enable": true}, "BFmhm018602": {"app": [], "update": 0, "enable": true}, "eufa20138": {"app": [], "update": 0, "enable": true}, "cxcpq74647": {"app": [], "update": 0, "enable": true}, "eocjn28022": {"app": [], "update": 0, "enable": true}, "siye4651": {"app": [], "update": 0, "enable": true}, "mlwpc56147": {"app": [], "update": 0, "enable": true}, "cohil140": {"app": [], "update": 0, "enable": true}, "yomnm88219": {"app": [], "update": 0, "enable": true}, "ocmy951762": {"app": [], "update": 0, "enable": true}, "bpqmndos": {"app": [], "update": 0, "enable": true}, "uhzni91671": {"app": [], "update": 0, "enable": true}, "eytk706972": {"app": [], "update": 0, "enable": true}, "gdz25343": {"app": [], "update": 0, "enable": true}, "dwlbl2u2": {"app": [], "update": 0, "enable": true}, "qmzzmnqsteam110": {"app": [], "update": 0, "enable": true}, "lehua131": {"app": [], "update": 0, "enable": true}, "pnfrp57903": {"app": [], "update": 0, "enable": true}, "zdnvj387": {"app": [], "update": 0, "enable": true}, "xn146646": {"app": [], "update": 0, "enable": true}, "wdz73568": {"app": [], "update": 0, "enable": true}, "st249451": {"app": [1847240, 1859370, 1164690, 613100, 1471280, 1009560, 2321830, 1885030], "update": 1707034922, "enable": true}, "upkfn31o": {"app": [], "update": 0, "enable": false, "status": 63}, "huabanmoni": {"app": [], "update": 0, "enable": false, "status": 43}, "cqthk582": {"app": [], "update": 0, "enable": true}, "gjpnq153": {"app": [], "update": 0, "enable": true}, "kplvh83654": {"app": [], "update": 0, "enable": true}, "injvl792": {"app": [], "update": 0, "enable": true}, "kebsh085": {"app": [], "update": 0, "enable": true}, "dmx10579": {"app": [], "update": 0, "enable": true}, "zcpbx169": {"app": [], "update": 0, "enable": true}, "flwb18745": {"app": [], "update": 0, "enable": true}, "tcny90882": {"app": [], "update": 0, "enable": true}, "wvfpc56149": {"app": [], "update": 0, "enable": true}, "hbpkq59025": {"app": [], "update": 0, "enable": true}, "bhxql785": {"app": [], "update": 0, "enable": true}, "sdfsdf665": {"app": [], "update": 0, "enable": true}, "qfux17738": {"app": [], "update": 0, "enable": true}, "1IG9R6IWO": {"app": [], "update": 0, "enable": true}, "vi650498": {"app": [], "update": 0, "enable": true}, "mrihn49617": {"app": [], "update": 0, "enable": true}, "qsj69534": {"app": [], "update": 0, "enable": true}, "nfosk822": {"app": [], "update": 0, "enable": true}, "uelxb30499": {"app": [], "update": 0, "enable": true}, "pa9825484": {"app": [], "update": 0, "enable": true}, "vdlxk60634": {"app": [], "update": 0, "enable": true}, "174e5fdb": {"app": [], "update": 0, "enable": true}, "dwin21678": {"app": [], "update": 0, "enable": true}, "zbfab710": {"app": [], "update": 0, "enable": true}, "iiyi75393": {"app": [], "update": 0, "enable": true}, "35Hs62jE727": {"app": [], "update": 0, "enable": true}, "qpwir55240": {"app": [], "update": 0, "enable": true}, "fqhez8960": {"app": [], "update": 0, "enable": true}, "xxojo10579": {"app": [], "update": 0, "enable": true}, "neqxd71987": {"app": [], "update": 0, "enable": true}, "mopkv99205": {"app": [], "update": 0, "enable": true}, "siye4722": {"app": [], "update": 0, "enable": true}, "qa3ro8ks6sf5": {"app": [], "update": 0, "enable": true}, "swqscs": {"app": [], "update": 0, "enable": true}, "fdjvz591": {"app": [], "update": 0, "enable": true}, "XWgyq753465": {"app": [], "update": 0, "enable": true}, "zx88996877": {"app": [], "update": 0, "enable": true}, "xsewa88283": {"app": [], "update": 0, "enable": true}, "xwaq25184": {"app": [], "update": 0, "enable": true}, "asdkd031": {"app": [], "update": 0, "enable": true}, "thvlu450": {"app": [], "update": 0, "enable": true}, "mucsy323": {"app": [], "update": 0, "enable": true}, "mine35728": {"app": [], "update": 0, "enable": true}, "8e06qW4FMZpzc3": {"app": [], "update": 0, "enable": true}, "wbtdx86014": {"app": [], "update": 0, "enable": true}, "izuvi156": {"app": [], "update": 0, "enable": true}, "Wmz20221201": {"app": [], "update": 0, "enable": true}, "ZZGGheM161": {"app": [], "update": 0, "enable": true}, "hnwt416": {"app": [], "update": 0, "enable": true}, "yyqeb202": {"app": [], "update": 0, "enable": true}, "gupur29622": {"app": [], "update": 0, "enable": true}, "easg70527": {"app": [], "update": 0, "enable": true}, "ewxw7966": {"app": [], "update": 0, "enable": true}, "iqzip143": {"app": [], "update": 0, "enable": true}, "it93008464": {"app": [], "update": 0, "enable": true}, "fwsl33468": {"app": [], "update": 0, "enable": true}, "ys5ci3hv4lu2": {"app": [], "update": 0, "enable": true}, "sawfp9753": {"app": [], "update": 0, "enable": true}, "ampersat254": {"app": [], "update": 0, "enable": true}, "oopqv41945": {"app": [], "update": 0, "enable": true}, "58SeoBpmS62": {"app": [], "update": 0, "enable": true}, "aaasss140Q": {"app": [], "update": 0, "enable": true}, "bihen9887": {"app": [1370140], "update": 1707034921, "enable": true}, "10227844": {"app": [2342950], "update": 1707034921, "enable": true}, "youzai6021": {"app": [1583230], "update": 1707034922, "enable": true}, "zmvuw47763": {"app": [1120320], "update": 1707034921, "enable": true}, "YXvel607661": {"app": [821880, 1120320, 624822, 724970], "update": 1707034924, "enable": true}, "axyif48890": {"app": [1524550, 2149610], "update": 1707033050, "enable": true}, "eddpm53076": {"app": [1637230, 893680, 1640300], "update": 1707034922, "enable": true}, "zwhrt77885": {"app": [], "update": 0, "enable": false, "status": 63}, "keqdr122": {"app": [1361510], "update": 1707033052, "enable": true}, "mhddy379004": {"app": [1980240], "update": 1707033052, "enable": true}, "wrrrt38467": {"app": [1956800], "update": 1707033052, "enable": true}, "Leyouzhai2022CCs": {"app": [], "update": 0, "enable": false, "status": 63}, "bflnb8188": {"app": [1412850], "update": 1707033053, "enable": true}, "tujr72028": {"app": [1597290], "update": 1707033052, "enable": true}, "teq7989": {"app": [1462040], "update": 1707033055, "enable": true}, "ejtd72888": {"app": [1038370, 1594250, 434190, 765930], "update": 1707034923, "enable": true}, "21519357": {"app": [311260], "update": 1707033056, "enable": true}, "twyi7837": {"app": [1562700], "update": 1707033054, "enable": true}, "pkju4242": {"app": [1811950], "update": 1707033056, "enable": true}, "jedka603": {"app": [], "update": 0, "enable": true}, "csccm372": {"app": [1904860], "update": 1707034924, "enable": true}, "hyqw78411": {"app": [], "update": 0, "enable": false, "status": 43}, "POHJGgxK": {"app": [], "update": 0, "enable": true}, "leyouzhai0031": {"app": [], "update": 0, "enable": true}, "lcfz92024": {"app": [], "update": 0, "enable": true}, "swhhjns": {"app": [], "update": 0, "enable": true}, "koang644": {"app": [], "update": 0, "enable": true}, "asgmgcs5f": {"app": [], "update": 0, "enable": true}, "gcw44831": {"app": [], "update": 0, "enable": true}, "yhkxx078": {"app": [], "update": 0, "enable": true}, "i4GwC3Qw": {"app": [], "update": 0, "enable": true}, "fopk46342": {"app": [], "update": 0, "enable": true}, "pq6ca2zk0tp9": {"app": [], "update": 0, "enable": true}, "khsqc013": {"app": [], "update": 0, "enable": true}, "phsw81379": {"app": [], "update": 0, "enable": true}, "pjvds80243": {"app": [], "update": 0, "enable": true}, "y8kvsfy9": {"app": [], "update": 0, "enable": true}, "bgt33173": {"app": [], "update": 0, "enable": true}, "dvodd41876": {"app": [], "update": 0, "enable": true}, "avbnn600": {"app": [], "update": 0, "enable": true}, "liugetu20879": {"app": [], "update": 0, "enable": true}, "liugetu2013": {"app": [], "update": 0, "enable": true}, "fri22982": {"app": [], "update": 0, "enable": true}, "ztxbi1757": {"app": [], "update": 0, "enable": true}, "liuge130xt1": {"app": [], "update": 0, "enable": true}, "liugetu20998": {"app": [], "update": 0, "enable": true}, "liuge52184": {"app": [], "update": 0, "enable": true}, "pdj24019": {"app": [], "update": 0, "enable": true}, "sad99250": {"app": [], "update": 0, "enable": true}, "gcz88139": {"app": [], "update": 0, "enable": true}, "dyo99523": {"app": [], "update": 0, "enable": true}, "yqkyv089": {"app": [], "update": 0, "enable": true}, "tqo76824": {"app": [], "update": 0, "enable": true}, "wtw77392": {"app": [], "update": 0, "enable": true}, "liuge1235ktu": {"app": [], "update": 0, "enable": true}, "vtapg098": {"app": [], "update": 0, "enable": true}, "dhtz7611": {"app": [], "update": 0, "enable": true}, "sic22550": {"app": [], "update": 0, "enable": true}, "vbng9385": {"app": [], "update": 0, "enable": true}, "hsner97398": {"app": [], "update": 0, "enable": true}, "rb815550": {"app": [], "update": 0, "enable": true}, "2ab22fb0": {"app": [], "update": 0, "enable": true}, "fm247054": {"app": [], "update": 0, "enable": true}, "ccw04275": {"app": [], "update": 0, "enable": true}, "liugetue5213": {"app": [], "update": 0, "enable": true}, "zfa13380": {"app": [], "update": 0, "enable": true}, "cqp71017": {"app": [], "update": 0, "enable": true}, "liugedsf521": {"app": [], "update": 0, "enable": true}, "xsvnx59462": {"app": [], "update": 0, "enable": true}, "CWPOHDwA": {"app": [], "update": 0, "enable": true}, "xyd34906": {"app": [], "update": 0, "enable": true}, "wusn77537": {"app": [], "update": 0, "enable": true}, "smx76123": {"app": [], "update": 0, "enable": true}, "j5mw1du7f": {"app": [], "update": 0, "enable": true}, "xbepe8g3": {"app": [], "update": 0, "enable": true}, "RK5h9SY3": {"app": [], "update": 0, "enable": true}, "kta27216": {"app": [], "update": 0, "enable": true}, "bk8tw6ex0sd8": {"app": [1065310], "update": 1707034925, "enable": true}, "7af0acb8": {"app": [1963210], "update": 1707034925, "enable": true}, "ybeif49u": {"app": [1451090, 2087050, 2087060], "update": 1707034924, "enable": true}, "kuh17835": {"app": [1816300], "update": 1707033272, "enable": true}, "Hk2Zl4Wf5Ro5": {"app": [1374970], "update": 1707033273, "enable": true}, "uvmoa11452": {"app": [849100], "update": 1707033275, "enable": true}, "bgj30786": {"app": [1337920], "update": 1707034925, "enable": true}, "ty0wg5zq2ur8": {"app": [1399080], "update": 1707033276, "enable": true}, "hlacs825": {"app": [312520], "update": 1707033278, "enable": true}, "jsr61725": {"app": [968250], "update": 1707033277, "enable": true}, "ewuiU307": {"app": [1475810, 1266430], "update": 1707033280, "enable": true}, "wxhl102": {"app": [], "update": 0, "enable": true}, "lgg90194": {"app": [1569200], "update": 1707033280, "enable": true}, "lxm71339": {"app": [1563130], "update": 1707034927, "enable": true}, "zwz44543": {"app": [1942280], "update": 1707034926, "enable": true}, "Zx7En0Ve1Ji7": {"app": [2067920], "update": 1707034926, "enable": true}, "daf12833": {"app": [1902710, 624822], "update": 1707033282, "enable": true}, "14802383": {"app": [1176470], "update": 1707034928, "enable": true}, "Jc7Nn8Wh0Wa0": {"app": [1850510], "update": 1707033284, "enable": true}, "63755888": {"app": [1337520], "update": 1707034927, "enable": true}, "cmj40637": {"app": [1135810], "update": 1707033284, "enable": true}, "nbn74969": {"app": [1831250], "update": 1707033283, "enable": true}, "35743308": {"app": [], "update": 0, "enable": true}, "liugeaesdeddfs": {"app": [], "update": 0, "enable": false, "status": 5}, "rrggt7186": {"app": [], "update": 0, "enable": true}, "zz5hj2ke0lh4": {"app": [], "update": 0, "enable": true}, "voq37370": {"app": [], "update": 0, "enable": true}, "scorn01z": {"app": [], "update": 0, "enable": true}, "qimo2553": {"app": [], "update": 0, "enable": true}, "Mw1Ez1Nu5Bz6": {"app": [], "update": 0, "enable": true}, "ulm75461": {"app": [], "update": 0, "enable": true}, "izm17616": {"app": [], "update": 0, "enable": true}, "ija13342": {"app": [], "update": 0, "enable": true}, "pic87501": {"app": [], "update": 0, "enable": true}, "ibx12418": {"app": [], "update": 0, "enable": true}, "ozvlk48816": {"app": [], "update": 0, "enable": true}, "sex13920": {"app": [], "update": 0, "enable": true}, "9SJ6UZJW1": {"app": [], "update": 0, "enable": true}, "hongchen35412": {"app": [], "update": 0, "enable": true}, "dv78273892": {"app": [], "update": 0, "enable": true}, "ygk63616": {"app": [], "update": 0, "enable": true}, "xqq34737": {"app": [], "update": 0, "enable": true}, "u6547854": {"app": [], "update": 0, "enable": true}, "rqjx27594": {"app": [], "update": 0, "enable": true}, "25215839": {"app": [], "update": 0, "enable": true}, "tqz86382": {"app": [], "update": 0, "enable": true}, "tei72890": {"app": [], "update": 0, "enable": true}, "pzr99395": {"app": [], "update": 0, "enable": true}, "myl59855": {"app": [], "update": 0, "enable": true}, "ppq26290": {"app": [], "update": 0, "enable": true}, "uba60178": {"app": [], "update": 0, "enable": true}, "kwl10928": {"app": [], "update": 0, "enable": true}, "gxs68431": {"app": [], "update": 0, "enable": true}, "junyi1201128": {"app": [], "update": 0, "enable": true}, "yrpu28431": {"app": [], "update": 0, "enable": true}, "xjp51751": {"app": [], "update": 0, "enable": true}, "36407651": {"app": [], "update": 0, "enable": true}, "Tq9Ig8Wb4Vh0": {"app": [], "update": 0, "enable": true}, "07379210": {"app": [], "update": 0, "enable": true}, "ew3iU338": {"app": [], "update": 0, "enable": true}, "zszoe74234": {"app": [], "update": 0, "enable": true}, "blg63101": {"app": [], "update": 0, "enable": true}, "xre12602": {"app": [], "update": 0, "enable": true}, "fvl86225": {"app": [], "update": 0, "enable": true}, "uRuEr1iURhf1": {"app": [], "update": 0, "enable": true}, "ewuiU303": {"app": [], "update": 0, "enable": true}, "tpy10011": {"app": [], "update": 0, "enable": true}, "tfu40809": {"app": [], "update": 0, "enable": true}, "bdq01305": {"app": [], "update": 0, "enable": true}, "zdc47479": {"app": [], "update": 0, "enable": true}, "jxf90802": {"app": [], "update": 0, "enable": true}, "hgrme16579": {"app": [], "update": 0, "enable": true}, "qSbLO33f": {"app": [], "update": 0, "enable": true}, "segfDaa": {"app": [], "update": 0, "enable": true}, "ps0bn4ei7tk1": {"app": [], "update": 0, "enable": true}, "wkg8235": {"app": [], "update": 0, "enable": true}, "hfavn72306": {"app": [], "update": 0, "enable": true}, "tk440920": {"app": [], "update": 0, "enable": true}, "bkrkv925": {"app": [], "update": 0, "enable": true}, "lyx95973": {"app": [], "update": 0, "enable": true}, "junyi1533316": {"app": [], "update": 0, "enable": true}, "bvc19840": {"app": [], "update": 0, "enable": true}, "7vWWUTC5": {"app": [], "update": 0, "enable": true}, "junyi25550120": {"app": [], "update": 0, "enable": true}, "k2bl8zgg": {"app": [], "update": 0, "enable": true}, "lrr53772": {"app": [], "update": 0, "enable": true}, "youzai5028": {"app": [], "update": 0, "enable": false, "status": 63}, "vhbtq78013": {"app": [2101080], "update": 1707033525, "enable": true}, "68227139": {"app": [16900], "update": 1707033527, "enable": true}, "ZKDLjShu": {"app": [1948980], "update": 1707033530, "enable": true}, "junyi1623022": {"app": [2004220], "update": 1707034928, "enable": true}, "7x8MKMKN": {"app": [1224020, 1550510, 1688410, 1761780, 2310120], "update": 1707034929, "enable": true}, "tuzxhoorgyly": {"app": [1571100], "update": 1707033531, "enable": true}, "19681525": {"app": [], "update": 0, "enable": false, "status": 43}, "xeg90847": {"app": [], "update": 0, "enable": true}, "jhuzz40819": {"app": [], "update": 0, "enable": true}, "junyi20239968": {"app": [], "update": 0, "enable": true}, "43699099": {"app": [], "update": 0, "enable": true}, "3217920036": {"app": [], "update": 0, "enable": true}, "dnhde94266": {"app": [], "update": 0, "enable": true}, "stagt0039": {"app": [], "update": 0, "enable": true}, "Vc3Tq4Ni0Rl4": {"app": [], "update": 0, "enable": true}, "aztsz52135": {"app": [], "update": 0, "enable": true}, "apqga75801": {"app": [], "update": 0, "enable": true}, "mulpd53784": {"app": [], "update": 0, "enable": true}, "M77vM5916": {"app": [], "update": 0, "enable": true}, "LUYMM0848": {"app": [], "update": 0, "enable": true}, "87731823": {"app": [], "update": 0, "enable": true}, "93612408": {"app": [], "update": 0, "enable": true}, "ke92vqTi": {"app": [], "update": 0, "enable": true}, "oxnjr40197": {"app": [], "update": 0, "enable": true}, "kfrpu57872": {"app": [], "update": 0, "enable": true}, "parjv36356": {"app": [], "update": 0, "enable": true}, "chebd138": {"app": [], "update": 0, "enable": true}, "kejyku221244": {"app": [], "update": 0, "enable": true}, "xgrni77548": {"app": [], "update": 0, "enable": true}, "qamcg77457": {"app": [], "update": 0, "enable": true}, "94485237": {"app": [], "update": 0, "enable": true}, "39668205": {"app": [], "update": 0, "enable": true}, "cfsig11826": {"app": [], "update": 0, "enable": true}, "wajueji228": {"app": [], "update": 0, "enable": true}, "qnyqx94266": {"app": [], "update": 0, "enable": true}, "Tn9Rs9Dy6Th7": {"app": [], "update": 0, "enable": true}, "43567357": {"app": [], "update": 0, "enable": true}, "77188602": {"app": [], "update": 0, "enable": true}, "dDv03827": {"app": [], "update": 0, "enable": true}, "yLrmq31417": {"app": [], "update": 0, "enable": true}, "wiqor64118": {"app": [], "update": 0, "enable": true}, "cesgs04957": {"app": [], "update": 0, "enable": true}, "u4cy62nq": {"app": [], "update": 0, "enable": true}, "33564090": {"app": [], "update": 0, "enable": true}, "21190782": {"app": [], "update": 0, "enable": true}, "xiybz45886": {"app": [], "update": 0, "enable": true}, "ctzda75846": {"app": [], "update": 0, "enable": true}, "D5750017": {"app": [], "update": 0, "enable": true}, "zqaxueb47639": {"app": [], "update": 0, "enable": true}, "00962851": {"app": [], "update": 0, "enable": true}, "junjun88866641": {"app": [], "update": 0, "enable": true}, "45080217": {"app": [], "update": 0, "enable": true}, "26158461": {"app": [], "update": 0, "enable": true}, "etykc785676": {"app": [], "update": 0, "enable": true}, "vmpbzakhgukc": {"app": [], "update": 0, "enable": true}, "72288699": {"app": [], "update": 0, "enable": true}, "mxhad458da": {"app": [], "update": 0, "enable": true}, "wgrpem": {"app": [], "update": 0, "enable": true}, "fffjy68947": {"app": [], "update": 0, "enable": true}, "banmagame77054": {"app": [], "update": 0, "enable": true}, "xjixw59394": {"app": [], "update": 0, "enable": true}, "byivh50589": {"app": [], "update": 0, "enable": true}, "17247526": {"app": [], "update": 0, "enable": true}, "ezzyw44136": {"app": [], "update": 0, "enable": true}, "kkzo66132": {"app": [], "update": 0, "enable": true}, "zhilang875": {"app": [], "update": 0, "enable": true}, "pandagame66476": {"app": [], "update": 0, "enable": true}, "firmanyukjozefina91": {"app": [], "update": 0, "enable": true}, "aaasss434Q": {"app": [], "update": 0, "enable": true}, "teq8014": {"app": [], "update": 0, "enable": true}, "hjynx": {"app": [], "update": 0, "enable": true}, "gvozxoyd": {"app": [1091500, 1495710, 624822], "update": 1707034930, "enable": true}, "16002064": {"app": [], "update": 0, "enable": true}, "9615OJFU214": {"app": [], "update": 0, "enable": false, "status": 43}, "glj52343": {"app": [], "update": 0, "enable": true}, "yuedongyouxi1223": {"app": [], "update": 0, "enable": true}, "36509115": {"app": [], "update": 0, "enable": true}, "99362382": {"app": [], "update": 0, "enable": true}, "gngtik": {"app": [], "update": 0, "enable": true}, "tnevx95759": {"app": [], "update": 0, "enable": true}, "39jctqqbfo93": {"app": [], "update": 0, "enable": true}, "hongchen99455": {"app": [], "update": 0, "enable": true}, "ncyxw78667": {"app": [], "update": 0, "enable": true}, "swmcwy": {"app": [], "update": 0, "enable": true}, "oxpu92258": {"app": [], "update": 0, "enable": true}, "5btmtm8jh": {"app": [], "update": 0, "enable": false, "status": 5}, "jghn43915": {"app": [], "update": 0, "enable": true}, "ykby84593": {"app": [], "update": 0, "enable": true}, "jvsc20776": {"app": [], "update": 0, "enable": true}, "dqur15306": {"app": [], "update": 0, "enable": true}, "chenxi45130": {"app": [], "update": 0, "enable": true}, "ceejk27878": {"app": [], "update": 0, "enable": true}, "44054914": {"app": [], "update": 0, "enable": true}, "kmyvq60136": {"app": [], "update": 0, "enable": true}, "liugew3eqweqwrul": {"app": [], "update": 0, "enable": true}, "yifrt96295": {"app": [], "update": 0, "enable": true}, "63733889": {"app": [], "update": 0, "enable": true}, "73994504": {"app": [], "update": 0, "enable": true}, "Hw4Lo6GL6Bz9": {"app": [], "update": 0, "enable": true}, "DyYjL699726": {"app": [], "update": 0, "enable": true}, "rijix90620": {"app": [], "update": 0, "enable": true}, "00064388": {"app": [], "update": 0, "enable": true}, "26843281t6": {"app": [], "update": 0, "enable": true}}